AUTHORS.rst
CONTRIBUTING.rst
HISTORY.rst
LICENSE
MANIFEST.in
README.rst
requirements-python-2.txt
requirements-python-3.txt
setup.cfg
setup.py
searchcmd/__init__.py
searchcmd/cache.py
searchcmd/cmdextract.py
searchcmd/commands.py
searchcmd/download.py
searchcmd/search_engines.py
searchcmd.egg-info/PKG-INFO
searchcmd.egg-info/SOURCES.txt
searchcmd.egg-info/dependency_links.txt
searchcmd.egg-info/entry_points.txt
searchcmd.egg-info/not-zip-safe
searchcmd.egg-info/pbr.json
searchcmd.egg-info/requires.txt
searchcmd.egg-info/top_level.txt
tests/__init__.py
tests/test_cache.py
tests/test_cmdextract.py
tests/test_commands.py
tests/test_download.py
tests/test_search_engines.py
tests/test_searchcmd.py
tests/testutils.py
tests/testdata/cmdextract/brunolinux.com
tests/testdata/cmdextract/cyberciti.biz
tests/testdata/cmdextract/stackoverflow.com
tests/testdata/cmdextract/unixmantra.com
tests/testdata/search_engines/bing.com
tests/testdata/search_engines/google.com