Metadata-Version: 1.1
Name: searchcmd
Version: 0.1.0
Summary: Search the internets for commands from the command line.
Home-page: https://github.com/jimmyppi/searchcmd/
Author: Jimmy Petersson
Author-email: jimmy.petersson@gmail.com
License: lite BSD
Keywords: searchcmd cli
Platform: UNKNOWN
Classifier: Development Status :: 4 - Beta
Classifier: Intended Audience :: Developers
Classifier: Intended Audience :: System Administrators
Classifier: License :: OSI Approved :: BSD License
Classifier: Natural Language :: English
Classifier: Programming Language :: Python :: 2
Classifier: Programming Language :: Python :: 2.7
Classifier: Programming Language :: Python :: 3
Classifier: Programming Language :: Python :: 3.4
Classifier: Operating System :: POSIX
Classifier: Environment :: Console
Classifier: Topic :: Software Development
Classifier: Topic :: System :: Systems Administration
